nstack/__init__.py
nstack-0.2.1.dist-info/METADATA
nstack-0.2.1.dist-info/RECORD
nstack-0.2.1.dist-info/WHEEL
nstack-0.2.1.dist-info/top_level.txt
