Metadata-Version: 2.1
Name: nstack
Version: 0.2.1
Summary: UNKNOWN
Home-page: UNKNOWN
Author: UNKNOWN
Author-email: UNKNOWN
License: UNKNOWN
Platform: UNKNOWN
Requires-Dist: six
Requires-Dist: contextdecorator
Requires-Dist: Events
